streamlit_react_jsonschema/__init__.py
streamlit_react_jsonschema/frontend/.env
streamlit_react_jsonschema/frontend/.prettierrc
streamlit_react_jsonschema/frontend/build/asset-manifest.json
streamlit_react_jsonschema/frontend/build/bootstrap.min.css
streamlit_react_jsonschema/frontend/build/index.html
streamlit_react_jsonschema/frontend/build/static/js/main.ad4c0531.js
streamlit_react_jsonschema/frontend/build/static/js/main.ad4c0531.js.LICENSE.txt
streamlit_react_jsonschema/frontend/build/static/js/main.ad4c0531.js.map
streamlit_react_jsonschema/frontend/package-lock.json
streamlit_react_jsonschema/frontend/package.json
streamlit_react_jsonschema/frontend/public/bootstrap.min.css
streamlit_react_jsonschema/frontend/public/index.html
streamlit_react_jsonschema/frontend/src/ReactJSONSchemaComponent.tsx
streamlit_react_jsonschema/frontend/src/index.tsx
streamlit_react_jsonschema/frontend/src/react-app-env.d.ts
streamlit_react_jsonschema/frontend/tsconfig.json
streamlit_react_jsonschema-0.1.6.dist-info/LICENSE
streamlit_react_jsonschema-0.1.6.dist-info/METADATA
streamlit_react_jsonschema-0.1.6.dist-info/WHEEL
streamlit_react_jsonschema-0.1.6.dist-info/RECORD
