Metadata-Version: 2.1
Name: streamlit_react_jsonschema
Version: 0.1.6
Summary: streamlit component for GhostOS, render form from JSONSchema by react-jsonschema-component
License: MIT
Author: ZhuMing
Author-email: thirdgerb@gmail.com
Requires-Python: >=3.8, !=2.7.*, !=3.0.*, !=3.1.*, !=3.2.*, !=3.3.*, !=3.4.*, !=3.5.*, !=3.6.*, !=3.7.*
Classifier: License :: OSI Approved :: MIT License
Classifier: Programming Language :: Python :: 3
Classifier: Programming Language :: Python :: 3.8
Classifier: Programming Language :: Python :: 3.9
Classifier: Programming Language :: Python :: 3.10
Classifier: Programming Language :: Python :: 3.11
Classifier: Programming Language :: Python :: 3.12
Requires-Dist: pydantic (>=2,<3)
Requires-Dist: streamlit (>=1.39.0,<2.0.0)
